rainwave_tools/__init__.py
rainwave_tools/album_search.py
rainwave_tools/apply_genres.py
rainwave_tools/assign_genres.py
rainwave_tools/cdg.py
rainwave_tools/cleanocr.py
rainwave_tools/delete_art.py
rainwave_tools/getocr.py
rainwave_tools/missing_art.py
rainwave_tools/move_ratings.py
rainwave_tools/normalize_filenames.py
rainwave_tools/ocra2ocr.py
rainwave_tools/ocremix.py
rainwave_tools/rename_artist.py
rainwave_tools/retag.py
rainwave_tools/rgwipe.py
rainwave_tools/rwtag.py
rainwave_tools/song_search.py
rainwave_tools/tit3_tit2.py
rainwave_tools/titles.py
rainwave_tools/url_check.py
rainwave_tools/utils.py
rainwave_tools-2026.0.dist-info/WHEEL
rainwave_tools-2026.0.dist-info/entry_points.txt
rainwave_tools-2026.0.dist-info/METADATA
rainwave_tools-2026.0.dist-info/RECORD
