Metadata-Version: 2.4
Name: rainwave-tools
Version: 2026.0
Summary: Tools for maintaining a local library of music for Rainwave
Author: William Jackson
Author-email: William Jackson <william@subtlecoolness.com>
License-Expression: MIT
Classifier: Programming Language :: Python :: 3
Classifier: Operating System :: OS Independent
Requires-Dist: lxml>=6.0.0
Requires-Dist: mutagen>=1.47.0
Requires-Dist: psycopg2-binary>=2.9.10
Requires-Dist: requests>=2.32.4
Requires-Python: >=3.10
Project-URL: Homepage, https://github.com/williamjacksn/rainwave-tools
Project-URL: Issues, https://github.com/williamjacksn/rainwave-tools/issues
